example/LiCoO2/Bader_calculation/ACF.dat
example/LiCoO2/Bader_calculation/OUTCAR
example/LiCoO2/Bader_calculation/POTCAR
example/LiCoO2/Bader_calculation/with_charges.traj
example/LiCoO2/Electronic_calculation/DOSCAR
example/LiCoO2/Energy_calculation/OUTCAR
example/LiCoO2/Intercalation/3_Li/1/geo_opt/OUTCAR
example/LiCoO2/Intercalation/3_Li/2/geo_opt/OUTCAR
example/LiCoO2/Intercalation/3_Li/3/geo_opt/OUTCAR
example/LiCoO2/Intercalation/3_Li/4/bader/ACF.dat
example/LiCoO2/Intercalation/3_Li/4/bader/OUTCAR
example/LiCoO2/Intercalation/3_Li/4/bader/with_charges.traj
example/LiCoO2/Intercalation/3_Li/4/dos/DOSCAR
example/LiCoO2/Intercalation/3_Li/4/geo_opt/OUTCAR
example/LiCoO2/Intercalation/6_Li/1/geo_opt/OUTCAR
example/LiCoO2/Intercalation/6_Li/2/bader/ACF.dat
example/LiCoO2/Intercalation/6_Li/2/bader/OUTCAR
example/LiCoO2/Intercalation/6_Li/2/bader/with_charges.traj
example/LiCoO2/Intercalation/6_Li/2/dos/DOSCAR
example/LiCoO2/Intercalation/6_Li/2/geo_opt/OUTCAR
lieme/__init__.py
lieme/featurize.py
lieme/ml.py
lieme/mpfetch.py
lieme/io/__init__.py
lieme/io/charges.py
lieme/io/dos.py
lieme-0.3.0.dist-info/licenses/LICENSE
lieme-0.3.0.dist-info/METADATA
lieme-0.3.0.dist-info/WHEEL
lieme-0.3.0.dist-info/top_level.txt
lieme-0.3.0.dist-info/RECORD
