Metadata-Version: 2.4
Name: lieme
Version: 0.3.0
Summary: Li-ion Intercalation Electrode Materials Exploration
Home-page: https://github.com/sreeharshab/lieme
Author: Sree Harsha Bhimineni
Author-email: Sree Harsha Bhimineni <bsreeharsha@g.ucla.edu>
License: MIT
Project-URL: Homepage, https://github.com/sreeharshab/lieme
Classifier: Development Status :: 3 - Alpha
Classifier: Intended Audience :: Science/Research
Classifier: License :: OSI Approved :: MIT License
Classifier: Operating System :: OS Independent
Classifier: Programming Language :: Python :: 3
Classifier: Programming Language :: Python :: 3.11
Classifier: Programming Language :: Python :: 3.12
Classifier: Programming Language :: Python :: 3.13
Requires-Python: >=3.11.0
License-File: LICENSE
Requires-Dist: tpot>=0.12.2
Requires-Dist: shap>=0.48.0
Requires-Dist: ase>=3.23.0
Requires-Dist: pymatgen>=2025.1.9
Requires-Dist: matminer>=0.9.3
Requires-Dist: mp-api>=0.45.3
Requires-Dist: openpyxl
Provides-Extra: dev
Requires-Dist: pytest; extra == "dev"
Requires-Dist: black; extra == "dev"
Requires-Dist: flake8; extra == "dev"
Dynamic: author
Dynamic: home-page
Dynamic: license-file
Dynamic: requires-python
